{
  "$schema": "../squarkdown/resources/squarkup-schema.json",

  "repo": "Squarkdown",

  "paths / site": "site",
  "paths / sources": [
    ".",
    "docs/"
  ],
  "paths / exclude": null,
  "paths / dest": "src/routes/(docs)/",
  "out / file-name": "~content",
  "out / site-data": "src/site.json",

  "opts / on-no-dir": ["warn", "create"],
  "opts / on-error": "kill",

  "bases / path": "src/parts/bases/",
  "bases / page.svelte": "~page.svelte",
  "bases / page.js": "~page.js",
  "styles / path": "src/styles/",
  "styles / page-styles": "src/styles/",
  "styles / base-style": "article",
  "assets / path": ".assets",
  "assets / site-assets": ".assets/site",
  "assets / extensions": [
    "jpg", "jpeg", "png", "svg", "ttf"
  ],
  "fonts / queries": [
    "Sora:wght@100..800"
  ]
}
